AUTHORS
CHANGES.rst
LICENSE
MANIFEST.in
README.rst
setup.cfg
setup.py
artwork/jinjalogo.svg
docs/Makefile
docs/api.rst
docs/cache_extension.py
docs/changelog.rst
docs/conf.py
docs/contents.rst.inc
docs/extensions.rst
docs/faq.rst
docs/index.rst
docs/integration.rst
docs/intro.rst
docs/jinjaext.py
docs/jinjastyle.sty
docs/latexindex.rst
docs/logo.pdf
docs/nativetypes.rst
docs/sandbox.rst
docs/switching.rst
docs/templates.rst
docs/tricks.rst
docs/_static/.ignore
docs/_static/jinja-small.png
docs/_templates/sidebarintro.html
docs/_templates/sidebarlogo.html
docs/_themes/LICENSE
docs/_themes/README
docs/_themes/jinja/layout.html
docs/_themes/jinja/relations.html
docs/_themes/jinja/theme.conf
docs/_themes/jinja/static/jinja.css_t
examples/bench.py
examples/profile.py
examples/basic/cycle.py
examples/basic/debugger.py
examples/basic/inheritance.py
examples/basic/test.py
examples/basic/test_filter_and_linestatements.py
examples/basic/test_loop_filter.py
examples/basic/translate.py
examples/basic/templates/broken.html
examples/basic/templates/subbroken.html
examples/rwbench/djangoext.py
examples/rwbench/rwbench.py
examples/rwbench/django/_form.html
examples/rwbench/django/_input_field.html
examples/rwbench/django/_textarea.html
examples/rwbench/django/index.html
examples/rwbench/django/layout.html
examples/rwbench/genshi/helpers.html
examples/rwbench/genshi/index.html
examples/rwbench/genshi/layout.html
examples/rwbench/jinja/helpers.html
examples/rwbench/jinja/index.html
examples/rwbench/jinja/layout.html
examples/rwbench/mako/helpers.html
examples/rwbench/mako/index.html
examples/rwbench/mako/layout.html
ext/djangojinja2.py
ext/inlinegettext.py
ext/jinja.el
ext/Vim/jinja.vim
ext/django2jinja/django2jinja.py
ext/django2jinja/example.py
ext/django2jinja/templates/index.html
ext/django2jinja/templates/layout.html
ext/django2jinja/templates/subtemplate.html
jinja2/__init__.py
jinja2/_compat.py
jinja2/_identifier.py
jinja2/asyncfilters.py
jinja2/asyncsupport.py
jinjamodificado.egg-info/PKG-INFO
jinjamodificado.egg-info/SOURCES.txt
jinjamodificado.egg-info/dependency_links.txt
jinjamodificado.egg-info/entry_points.txt
jinjamodificado.egg-info/not-zip-safe
jinjamodificado.egg-info/requires.txt
jinjamodificado.egg-info/top_level.txt
