Metadata-Version: 1.1
Name: jinjamodificado
Version: 2.10
Summary: Jinja Modificado engine written in pure python.
Home-page: https://gitlab.com/israelblender/jinja_modificado
Author: Armin Ronacher
Author-email: armin.ronacher@active-4.com
License: BSD
Download-URL: https://gitlab.com/israelblender/jinja_modificado/repository/archive.tar.gz?ref=0.1
Platform: UNKNOWN
Classifier: Development Status :: 5 - Production/Stable
Classifier: Environment :: Web Environment
Classifier: Intended Audience :: Developers
Classifier: License :: OSI Approved :: BSD License
Classifier: Operating System :: OS Independent
Classifier: Programming Language :: Python
Classifier: Programming Language :: Python :: 2
Classifier: Programming Language :: Python :: 2.6
Classifier: Programming Language :: Python :: 2.7
Classifier: Programming Language :: Python :: 3
Classifier: Programming Language :: Python :: 3.3
Classifier: Programming Language :: Python :: 3.4
Classifier: Programming Language :: Python :: 3.5
Classifier: Programming Language :: Python :: 3.6
Classifier: Topic :: Internet :: WWW/HTTP :: Dynamic Content
Classifier: Topic :: Software Development :: Libraries :: Python Modules
Classifier: Topic :: Text Processing :: Markup :: HTML
